current/__init__.py
current/py.typed
current-0.5.dist-info/licenses/LICENSE.txt
current-0.5.dist-info/METADATA
current-0.5.dist-info/WHEEL
current-0.5.dist-info/top_level.txt
current-0.5.dist-info/RECORD
