Metadata-Version: 2.4
Name: current
Version: 0.5
Summary: Current module relative paths and imports
Author-email: Sebastian Bank <sebastian.bank@uni-leipzig.de>
License-Expression: CC0-1.0
Project-URL: Homepage, https://github.com/xflr6/current
Project-URL: Issue Tracker, https://github.com/xflr6/current/issues
Project-URL: CI, https://github.com/xflr6/current/actions
Project-URL: Coverage, https://codecov.io/gh/xflr6/current
Keywords: sys.path,import,temporary,inspect,caller
Platform: any
Classifier: Development Status :: 4 - Beta
Classifier: Intended Audience :: Developers
Classifier: Operating System :: OS Independent
Classifier: Programming Language :: Python :: 3
Classifier: Programming Language :: Python :: 3.10
Classifier: Programming Language :: Python :: 3.11
Classifier: Programming Language :: Python :: 3.12
Classifier: Programming Language :: Python :: 3.13
Classifier: Programming Language :: Python :: 3.14
Requires-Python: >=3.10
License-File: LICENSE.txt
Provides-Extra: dev
Requires-Dist: build; extra == "dev"
Requires-Dist: wheel; extra == "dev"
Requires-Dist: twine; extra == "dev"
Requires-Dist: mypy; extra == "dev"
Requires-Dist: flake8; extra == "dev"
Requires-Dist: Flake8-pyproject; extra == "dev"
Requires-Dist: pep8-naming; extra == "dev"
Requires-Dist: tox>=4; extra == "dev"
Provides-Extra: test
Requires-Dist: pytest>=8; extra == "test"
Requires-Dist: pytest-cov; extra == "test"
Requires-Dist: coverage; extra == "test"
Dynamic: license-file
